berri_ai/ComplexInformationQA.py
berri_ai/DocStore.py
berri_ai/QAAgent.py
berri_ai/__init__.py
berri_ai/agents/DataAnalysisPrompt.py
berri_ai/agents/DataAnalysisQA.py
berri_ai/search_strategies/bm25/DocStore.py
berri_ai/search_strategies/bm25/DocStore_CSV.py
berri_ai/search_strategies/pipelines/QAGenDocPipeline.py
berri_ai/search_strategies/pipelines/SummarizationDocPipeline.py
berri_ai-0.21.3.dist-info/WHEEL
berri_ai-0.21.3.dist-info/METADATA
berri_ai-0.21.3.dist-info/RECORD
