Metadata-Version: 2.1
Name: berri-ai
Version: 0.21.3
Summary: 
Author: Team Berri
Author-email: clerkieai@gmail.com
Requires-Python: >=3.8.1,<4.0.0
Classifier: Programming Language :: Python :: 3
Classifier: Programming Language :: Python :: 3.10
Classifier: Programming Language :: Python :: 3.9
Requires-Dist: fuzzywuzzy (>=0.18.0,<0.19.0)
Requires-Dist: html2text (>=2020.1.16,<2021.0.0)
Requires-Dist: llama-index (==0.4.34)
Requires-Dist: mixpanel (>=4.10.0,<5.0.0)
Requires-Dist: nltk (>=3.8.1,<4.0.0)
Requires-Dist: numpy (>=1.18,<2.0)
Requires-Dist: openai (>=0.27.2,<0.28.0)
Requires-Dist: pipreqs (>=0.4.11,<0.5.0)
Requires-Dist: rank-bm25 (>=0.2.2,<0.3.0)
Requires-Dist: requests (>=2.28.2,<3.0.0)
Requires-Dist: tiktoken (>=0.2.0,<0.3.0)
Requires-Dist: tqdm (>=4.64.1,<5.0.0)
